golfy/__init__.py
golfy/deconvolution.py
golfy/design.py
golfy/evaluation.py
golfy/initialization.py
golfy/main.py
golfy/merging.py
golfy/optimization.py
golfy/simulation.py
golfy/types.py
golfy/util.py
golfy/validity.py
golfy-2.5.2.dist-info/LICENSE
golfy-2.5.2.dist-info/METADATA
golfy-2.5.2.dist-info/WHEEL
golfy-2.5.2.dist-info/top_level.txt
golfy-2.5.2.dist-info/RECORD
