Metadata-Version: 2.1
Name: golfy
Version: 2.5.2
Summary: Heuristic peptide pool optimization for ELISpot and other immunological assays
Author-email: Alex Rubinsteyn <alex.rubinsteyn@unc.edu>
Project-URL: Homepage, https://github.com/pirl-unc/golfy
Project-URL: Bug Tracker, https://github.com/pirl-unc/golfy
Classifier: Programming Language :: Python :: Implementation :: CPython
Classifier: Environment :: Console
Classifier: Operating System :: OS Independent
Classifier: Intended Audience :: Science/Research
Classifier: License :: OSI Approved :: Apache Software License
Classifier: Topic :: Scientific/Engineering :: Bio-Informatics
Requires-Python: >=3.7
License-File: LICENSE
Requires-Dist: numpy <2.0.0,>=1.0.0
Requires-Dist: scikit-learn <2.0.0,>=1.2.0
